title_prettier/__init__.py
title_prettier/titles.py
title_prettier/web.py
title_prettier-0.0.1.dist-info/LICENSE
title_prettier-0.0.1.dist-info/METADATA
title_prettier-0.0.1.dist-info/WHEEL
title_prettier-0.0.1.dist-info/top_level.txt
title_prettier-0.0.1.dist-info/RECORD
